build/lib/unquietcode/tools/runbook/__init__.py
build/lib/unquietcode/tools/runbook/annotations.py
build/lib/unquietcode/tools/runbook/runbook.py
build/lib/unquietcode/tools/runbook/step.py
unquietcode/tools/runbook/__init__.py
unquietcode/tools/runbook/annotations.py
unquietcode/tools/runbook/runbook.py
unquietcode/tools/runbook/step.py
runbook-0.1.dist-info/METADATA
runbook-0.1.dist-info/WHEEL
runbook-0.1.dist-info/top_level.txt
runbook-0.1.dist-info/RECORD
