Metadata-Version: 2.1
Name: runbook
Version: 0.1
Summary: a tool for defining repeatable processes in code
Home-page: https://github.com/UnquietCode/runbook.py
Author: Benjamin Fagin
Author-email: blouis@unquietcode.com
License: UNKNOWN
Platform: UNKNOWN
Classifier: Programming Language :: Python :: 3
Classifier: License :: OSI Approved :: Apache Software License
Classifier: Operating System :: OS Independent
